turpy/__init__.py
turpy/geospatial/__init__.py
turpy/hexagon/__init__.py
turpy/hexagon/h3tools.py
turpy/io/__init__.py
turpy/io/load_yaml.py
turpy/utils/__init__.py
turpy-0.3.2.dist-info/LICENSE.txt
turpy-0.3.2.dist-info/WHEEL
turpy-0.3.2.dist-info/METADATA
turpy-0.3.2.dist-info/RECORD
