Metadata-Version: 2.1
Name: turpy
Version: 0.3.2
Summary: Example project of useful code published as python module to PyPi.
Author: Jose Beltran
Author-email: drjobel.connection@gmail.com
Requires-Python: >=3.8,<4.0
Classifier: Programming Language :: Python :: 3
Classifier: Programming Language :: Python :: 3.8
Classifier: Programming Language :: Python :: 3.9
Requires-Dist: PyYAML (>=5.4.1,<6.0.0)
